[
  {
    "lint": "cicasgen_when_version_present_version_eq_31349",
    "fires": 1075,
    "applies": 1077,
    "error_frac": 0.998,
    "REAL": 984,
    "SPURIOUS": 91,
    "UNCERTAIN": 0,
    "suspect": true
  },
  {
    "lint": "cicasgen_oid_eq_oid_ec_public_key_29539",
    "fires": 826,
    "applies": 1034,
    "error_frac": 0.799,
    "REAL": 752,
    "SPURIOUS": 74,
    "UNCERTAIN": 0,
    "suspect": true
  },
  {
    "lint": "cicasgen_subject_alternate_name_critical_31132",
    "fires": 695,
    "applies": 1077,
    "error_frac": 0.645,
    "REAL": 636,
    "SPURIOUS": 59,
    "UNCERTAIN": 0,
    "suspect": true
  },
  {
    "lint": "cicasgen_bytes_eq_31102",
    "fires": 240,
    "applies": 259,
    "error_frac": 0.927,
    "REAL": 208,
    "SPURIOUS": 32,
    "UNCERTAIN": 0,
    "suspect": true
  },
  {
    "lint": "cicasgen_subject_alt_name_present_31065",
    "fires": 365,
    "applies": 1077,
    "error_frac": 0.339,
    "REAL": 333,
    "SPURIOUS": 32,
    "UNCERTAIN": 0,
    "suspect": true
  },
  {
    "lint": "cicasgen_permitted_directory_names_present_29375",
    "fires": 186,
    "applies": 233,
    "error_frac": 0.798,
    "REAL": 160,
    "SPURIOUS": 26,
    "UNCERTAIN": 0,
    "suspect": true
  },
  {
    "lint": "cicasgen_when_oid_policy_organization_validated_list_contains_29476",
    "fires": 127,
    "applies": 215,
    "error_frac": 0.591,
    "REAL": 107,
    "SPURIOUS": 20,
    "UNCERTAIN": 0,
    "suspect": true
  },
  {
    "lint": "cicasgen_policy_identifiers_count_and_any_policy_list_contains_29339",
    "fires": 200,
    "applies": 233,
    "error_frac": 0.858,
    "REAL": 190,
    "SPURIOUS": 10,
    "UNCERTAIN": 0,
    "suspect": true
  },
  {
    "lint": "cicasgen_when_oid_policy_individual_validated_list_contains_29446",
    "fires": 18,
    "applies": 31,
    "error_frac": 0.581,
    "REAL": 17,
    "SPURIOUS": 1,
    "UNCERTAIN": 0,
    "suspect": true
  },
  {
    "lint": "cicasgen_when_oid_policy_individual_validated_list_contains_29447",
    "fires": 10,
    "applies": 31,
    "error_frac": 0.323,
    "REAL": 9,
    "SPURIOUS": 1,
    "UNCERTAIN": 0,
    "suspect": true
  },
  {
    "lint": "cicasgen_when_is_ca_when_is_ca_cross_field_eq_31400",
    "fires": 228,
    "applies": 1077,
    "error_frac": 0.212,
    "REAL": 201,
    "SPURIOUS": 1,
    "UNCERTAIN": 26,
    "suspect": true
  },
  {
    "lint": "cicasgen_when_oid_policy_individual_validated_list_contains_29448",
    "fires": 15,
    "applies": 31,
    "error_frac": 0.484,
    "REAL": 15,
    "SPURIOUS": 0,
    "UNCERTAIN": 0,
    "suspect": true
  },
  {
    "lint": "cicasgen_when_subscriber_cert_dnsnames_present_or_ipaddresses_29414",
    "fires": 246,
    "applies": 748,
    "error_frac": 0.329,
    "REAL": 246,
    "SPURIOUS": 0,
    "UNCERTAIN": 0,
    "suspect": true
  },
  {
    "lint": "cicasgen_subject_alternate_name_critical_29800",
    "fires": 13,
    "applies": 62,
    "error_frac": 0.21,
    "REAL": 12,
    "SPURIOUS": 0,
    "UNCERTAIN": 1,
    "suspect": false
  },
  {
    "lint": "cicasgen_excluded_directory_names_absent_and_excluded_dnsnames_29269",
    "fires": 53,
    "applies": 257,
    "error_frac": 0.206,
    "REAL": 53,
    "SPURIOUS": 0,
    "UNCERTAIN": 0,
    "suspect": false
  },
  {
    "lint": "cicasgen_policy_identifiers_count_29316",
    "fires": 42,
    "applies": 233,
    "error_frac": 0.18,
    "REAL": 40,
    "SPURIOUS": 0,
    "UNCERTAIN": 2,
    "suspect": false
  },
  {
    "lint": "cicasgen_ku_has_cert_sign_or_ku_has_digital_signature_or_ku_has_29408",
    "fires": 88,
    "applies": 545,
    "error_frac": 0.161,
    "REAL": 88,
    "SPURIOUS": 0,
    "UNCERTAIN": 0,
    "suspect": false
  },
  {
    "lint": "cicasgen_not_any_policy_list_contains_29324",
    "fires": 36,
    "applies": 233,
    "error_frac": 0.155,
    "REAL": 20,
    "SPURIOUS": 0,
    "UNCERTAIN": 16,
    "suspect": false
  },
  {
    "lint": "cicasgen_not_any_policy_list_contains_29325",
    "fires": 36,
    "applies": 233,
    "error_frac": 0.155,
    "REAL": 20,
    "SPURIOUS": 0,
    "UNCERTAIN": 16,
    "suspect": false
  },
  {
    "lint": "cicasgen_not_any_policy_list_contains_29342",
    "fires": 36,
    "applies": 233,
    "error_frac": 0.155,
    "REAL": 20,
    "SPURIOUS": 0,
    "UNCERTAIN": 16,
    "suspect": false
  },
  {
    "lint": "cicasgen_not_any_policy_list_contains_29343",
    "fires": 36,
    "applies": 233,
    "error_frac": 0.155,
    "REAL": 20,
    "SPURIOUS": 0,
    "UNCERTAIN": 16,
    "suspect": false
  },
  {
    "lint": "cicasgen_when_not_subject_locality_present_subject_province_29433",
    "fires": 4,
    "applies": 31,
    "error_frac": 0.129,
    "REAL": 4,
    "SPURIOUS": 0,
    "UNCERTAIN": 0,
    "suspect": false
  },
  {
    "lint": "cicasgen_not_dn_empty_issuer_31108",
    "fires": 90,
    "applies": 1077,
    "error_frac": 0.084,
    "REAL": 89,
    "SPURIOUS": 0,
    "UNCERTAIN": 1,
    "suspect": false
  },
  {
    "lint": "cicasgen_not_ext_subfield_present_authority_key_id_28730",
    "fires": 20,
    "applies": 257,
    "error_frac": 0.078,
    "REAL": 20,
    "SPURIOUS": 0,
    "UNCERTAIN": 0,
    "suspect": false
  },
  {
    "lint": "cicasgen_issuer_unique_id_absent_29298",
    "fires": 15,
    "applies": 233,
    "error_frac": 0.064,
    "REAL": 15,
    "SPURIOUS": 0,
    "UNCERTAIN": 0,
    "suspect": false
  },
  {
    "lint": "cicasgen_issuer_unique_id_absent_29332",
    "fires": 15,
    "applies": 233,
    "error_frac": 0.064,
    "REAL": 15,
    "SPURIOUS": 0,
    "UNCERTAIN": 0,
    "suspect": false
  },
  {
    "lint": "cicasgen_issuer_unique_id_absent_29358",
    "fires": 15,
    "applies": 233,
    "error_frac": 0.064,
    "REAL": 15,
    "SPURIOUS": 0,
    "UNCERTAIN": 0,
    "suspect": false
  },
  {
    "lint": "cicasgen_issuer_unique_id_absent_29365",
    "fires": 15,
    "applies": 233,
    "error_frac": 0.064,
    "REAL": 15,
    "SPURIOUS": 0,
    "UNCERTAIN": 0,
    "suspect": false
  },
  {
    "lint": "cicasgen_when_oid_policy_organization_validated_list_contains_29463",
    "fires": 10,
    "applies": 215,
    "error_frac": 0.047,
    "REAL": 8,
    "SPURIOUS": 0,
    "UNCERTAIN": 2,
    "suspect": false
  },
  {
    "lint": "cicasgen_when_subscriber_cert_not_any_policy_list_contains_29493",
    "fires": 26,
    "applies": 748,
    "error_frac": 0.035,
    "REAL": 26,
    "SPURIOUS": 0,
    "UNCERTAIN": 0,
    "suspect": false
  },
  {
    "lint": "cicasgen_when_not_subject_locality_present_subject_province_29460",
    "fires": 7,
    "applies": 215,
    "error_frac": 0.033,
    "REAL": 7,
    "SPURIOUS": 0,
    "UNCERTAIN": 0,
    "suspect": false
  },
  {
    "lint": "cicasgen_when_not_subject_province_present_subject_locality_29465",
    "fires": 7,
    "applies": 215,
    "error_frac": 0.033,
    "REAL": 7,
    "SPURIOUS": 0,
    "UNCERTAIN": 0,
    "suspect": false
  },
  {
    "lint": "cicasgen_authority_key_id_present_29273",
    "fires": 7,
    "applies": 233,
    "error_frac": 0.03,
    "REAL": 7,
    "SPURIOUS": 0,
    "UNCERTAIN": 0,
    "suspect": false
  },
  {
    "lint": "cicasgen_issuer_unique_id_absent_and_subject_unique_id_absent_31183",
    "fires": 23,
    "applies": 1077,
    "error_frac": 0.021,
    "REAL": 23,
    "SPURIOUS": 0,
    "UNCERTAIN": 0,
    "suspect": false
  },
  {
    "lint": "cicasgen_when_version_present_version_eq_31172",
    "fires": 18,
    "applies": 1077,
    "error_frac": 0.017,
    "REAL": 18,
    "SPURIOUS": 0,
    "UNCERTAIN": 0,
    "suspect": false
  },
  {
    "lint": "cicasgen_when_version_present_version_eq_31344",
    "fires": 18,
    "applies": 1077,
    "error_frac": 0.017,
    "REAL": 18,
    "SPURIOUS": 0,
    "UNCERTAIN": 0,
    "suspect": false
  },
  {
    "lint": "cicasgen_not_ext_subfield_present_authority_key_id_29274",
    "fires": 4,
    "applies": 257,
    "error_frac": 0.016,
    "REAL": 4,
    "SPURIOUS": 0,
    "UNCERTAIN": 0,
    "suspect": false
  },
  {
    "lint": "cicasgen_when_version_present_version_in_set_31169",
    "fires": 16,
    "applies": 1077,
    "error_frac": 0.015,
    "REAL": 16,
    "SPURIOUS": 0,
    "UNCERTAIN": 0,
    "suspect": false
  },
  {
    "lint": "cicasgen_when_version_present_version_in_set_31342",
    "fires": 16,
    "applies": 1077,
    "error_frac": 0.015,
    "REAL": 16,
    "SPURIOUS": 0,
    "UNCERTAIN": 0,
    "suspect": false
  },
  {
    "lint": "cicasgen_serial_number_len_31163",
    "fires": 13,
    "applies": 1077,
    "error_frac": 0.012,
    "REAL": 13,
    "SPURIOUS": 0,
    "UNCERTAIN": 0,
    "suspect": false
  },
  {
    "lint": "cicasgen_when_eku_has_any_ext_key_usage_count_28713",
    "fires": 2,
    "applies": 233,
    "error_frac": 0.009,
    "REAL": 2,
    "SPURIOUS": 0,
    "UNCERTAIN": 0,
    "suspect": false
  },
  {
    "lint": "cicasgen_when_oid_policy_organization_validated_list_contains_29474",
    "fires": 2,
    "applies": 215,
    "error_frac": 0.009,
    "REAL": 1,
    "SPURIOUS": 0,
    "UNCERTAIN": 1,
    "suspect": false
  },
  {
    "lint": "cicasgen_when_oid_policy_organization_validated_list_contains_29475",
    "fires": 2,
    "applies": 215,
    "error_frac": 0.009,
    "REAL": 1,
    "SPURIOUS": 0,
    "UNCERTAIN": 1,
    "suspect": false
  },
  {
    "lint": "cicasgen_when_subscriber_cert_issuer_unique_id_absent_29397",
    "fires": 6,
    "applies": 748,
    "error_frac": 0.008,
    "REAL": 6,
    "SPURIOUS": 0,
    "UNCERTAIN": 0,
    "suspect": false
  },
  {
    "lint": "cicasgen_not_cert_policy_explicit_text_has_encoding_tag_in_set_30984",
    "fires": 6,
    "applies": 1077,
    "error_frac": 0.006,
    "REAL": 6,
    "SPURIOUS": 0,
    "UNCERTAIN": 0,
    "suspect": false
  },
  {
    "lint": "cicasgen_subject_alternate_name_not_critical_31067",
    "fires": 4,
    "applies": 685,
    "error_frac": 0.006,
    "REAL": 4,
    "SPURIOUS": 0,
    "UNCERTAIN": 0,
    "suspect": false
  },
  {
    "lint": "cicasgen_sig_alg_matches_tbssignature_29300",
    "fires": 1,
    "applies": 233,
    "error_frac": 0.004,
    "REAL": 1,
    "SPURIOUS": 0,
    "UNCERTAIN": 0,
    "suspect": false
  },
  {
    "lint": "cicasgen_sig_alg_matches_tbssignature_29334",
    "fires": 1,
    "applies": 233,
    "error_frac": 0.004,
    "REAL": 1,
    "SPURIOUS": 0,
    "UNCERTAIN": 0,
    "suspect": false
  },
  {
    "lint": "cicasgen_sig_alg_matches_tbssignature_29367",
    "fires": 1,
    "applies": 233,
    "error_frac": 0.004,
    "REAL": 1,
    "SPURIOUS": 0,
    "UNCERTAIN": 0,
    "suspect": false
  },
  {
    "lint": "cicasgen_sig_alg_matches_tbssignature_31396",
    "fires": 4,
    "applies": 1077,
    "error_frac": 0.004,
    "REAL": 4,
    "SPURIOUS": 0,
    "UNCERTAIN": 0,
    "suspect": false
  },
  {
    "lint": "cicasgen_subject_unique_id_absent_29299",
    "fires": 1,
    "applies": 233,
    "error_frac": 0.004,
    "REAL": 1,
    "SPURIOUS": 0,
    "UNCERTAIN": 0,
    "suspect": false
  },
  {
    "lint": "cicasgen_subject_unique_id_absent_29333",
    "fires": 1,
    "applies": 233,
    "error_frac": 0.004,
    "REAL": 1,
    "SPURIOUS": 0,
    "UNCERTAIN": 0,
    "suspect": false
  },
  {
    "lint": "cicasgen_subject_unique_id_absent_29359",
    "fires": 1,
    "applies": 233,
    "error_frac": 0.004,
    "REAL": 1,
    "SPURIOUS": 0,
    "UNCERTAIN": 0,
    "suspect": false
  },
  {
    "lint": "cicasgen_subject_unique_id_absent_29366",
    "fires": 1,
    "applies": 233,
    "error_frac": 0.004,
    "REAL": 1,
    "SPURIOUS": 0,
    "UNCERTAIN": 0,
    "suspect": false
  },
  {
    "lint": "cicasgen_when_crl_dist_present_crldistribution_points_count_29735",
    "fires": 1,
    "applies": 257,
    "error_frac": 0.004,
    "REAL": 1,
    "SPURIOUS": 0,
    "UNCERTAIN": 0,
    "suspect": false
  },
  {
    "lint": "cicasgen_when_root_ca_not_crl_dist_present_29288",
    "fires": 1,
    "applies": 257,
    "error_frac": 0.004,
    "REAL": 1,
    "SPURIOUS": 0,
    "UNCERTAIN": 0,
    "suspect": false
  },
  {
    "lint": "cicasgen_when_subscriber_cert_subject_alt_name_not_critical_29415",
    "fires": 3,
    "applies": 748,
    "error_frac": 0.004,
    "REAL": 3,
    "SPURIOUS": 0,
    "UNCERTAIN": 0,
    "suspect": false
  },
  {
    "lint": "cicasgen_when_extensions_present_version_eq_31403",
    "fires": 3,
    "applies": 1077,
    "error_frac": 0.003,
    "REAL": 3,
    "SPURIOUS": 0,
    "UNCERTAIN": 0,
    "suspect": false
  },
  {
    "lint": "cicasgen_serial_number_value_31123",
    "fires": 2,
    "applies": 1077,
    "error_frac": 0.002,
    "REAL": 2,
    "SPURIOUS": 0,
    "UNCERTAIN": 0,
    "suspect": false
  },
  {
    "lint": "cicasgen_serial_number_value_31161",
    "fires": 2,
    "applies": 1077,
    "error_frac": 0.002,
    "REAL": 2,
    "SPURIOUS": 0,
    "UNCERTAIN": 0,
    "suspect": false
  },
  {
    "lint": "cicasgen_when_cert_policy_present_policy_identifiers_count_29491",
    "fires": 1,
    "applies": 748,
    "error_frac": 0.001,
    "REAL": 1,
    "SPURIOUS": 0,
    "UNCERTAIN": 0,
    "suspect": false
  },
  {
    "lint": "cicasgen_when_pre_certificate_signing_certificate_eku_list_29533",
    "fires": 1,
    "applies": 981,
    "error_frac": 0.001,
    "REAL": 1,
    "SPURIOUS": 0,
    "UNCERTAIN": 0,
    "suspect": false
  },
  {
    "lint": "cicasgen_when_subscriber_cert_not_aiahas_method_other_than_29484",
    "fires": 1,
    "applies": 748,
    "error_frac": 0.001,
    "REAL": 1,
    "SPURIOUS": 0,
    "UNCERTAIN": 0,
    "suspect": false
  },
  {
    "lint": "cicasgen_when_subscriber_cert_not_path_len_constraint_present_29490",
    "fires": 1,
    "applies": 748,
    "error_frac": 0.001,
    "REAL": 1,
    "SPURIOUS": 0,
    "UNCERTAIN": 0,
    "suspect": false
  }
]